spurl/__init__.py
spurl/models.py
spurl/tests.py
spurl/templatetags/__init__.py
spurl/templatetags/spurl.py
django_spurl-0.6.8.dist-info/METADATA
django_spurl-0.6.8.dist-info/WHEEL
django_spurl-0.6.8.dist-info/top_level.txt
django_spurl-0.6.8.dist-info/RECORD
