Metadata-Version: 2.1
Name: django-spurl
Version: 0.6.8
Summary: A Django template library for manipulating URLs.
Home-page: https://github.com/j4mie/django-spurl/
Author: Jamie Matthews
Author-email: jamie.matthews@jamesturk.net
Maintainer: Basil Shubin
Maintainer-email: basil.shubin@gmail.com
License: Public Domain
Download-URL: https://github.com/j4mie/django-spurl/zipball/master
Platform: UNKNOWN
Classifier: Development Status :: 5 - Production/Stable
Classifier: Environment :: Web Environment
Classifier: Intended Audience :: Developers
Classifier: License :: Public Domain
Classifier: Operating System :: OS Independent
Classifier: Programming Language :: Python
Classifier: Programming Language :: Python :: 3 :: Only
Classifier: Programming Language :: Python :: 3.6
Classifier: Programming Language :: Python :: 3.7
Classifier: Programming Language :: Python :: 3.8
Classifier: Programming Language :: Python :: 3.9
Classifier: Framework :: Django
Classifier: Framework :: Django :: 2.2
Classifier: Framework :: Django :: 3.0
Classifier: Framework :: Django :: 3.1
Classifier: Framework :: Django :: 3.2
Provides-Extra: develop
Provides-Extra: test
